nova_mksproxy-0.0.2.dist-info/DESCRIPTION.rst
nova_mksproxy-0.0.2.dist-info/METADATA
nova_mksproxy-0.0.2.dist-info/RECORD
nova_mksproxy-0.0.2.dist-info/WHEEL
nova_mksproxy-0.0.2.dist-info/entry_points.txt
nova_mksproxy-0.0.2.dist-info/metadata.json
nova_mksproxy-0.0.2.dist-info/pbr.json
nova_mksproxy-0.0.2.dist-info/top_level.txt
novaproxy/__init__.py
novaproxy/authd.py
novaproxy/mksproxy.py
novaproxy/tests/__init__.py
novaproxy/tests/test_authd.py
